polycrud/__init__.py
polycrud/connectors/__init__.py
polycrud/connectors/base.py
polycrud/connectors/mongo/__init__.py
polycrud/connectors/mongo/_model.py
polycrud/connectors/mongo/async_mongo.py
polycrud/connectors/mongo/sync_mongo.py
polycrud/connectors/mysql/__init__.py
polycrud/connectors/mysql/async_mysql.py
polycrud/connectors/mysql/sync_mysql.py
polycrud/connectors/opensearch/__init__.py
polycrud/connectors/opensearch/_async_opensearch.py
polycrud/connectors/opensearch/_sync_opensearch.py
polycrud/connectors/postgres/__init__.py
polycrud/connectors/postgres/async_postgres.py
polycrud/connectors/postgres/sync_postgres.py
polycrud/connectors/pyredis/__init__.py
polycrud/connectors/pyredis/_async_redis.py
polycrud/connectors/pyredis/_base.py
polycrud/connectors/pyredis/_sync_redis.py
polycrud/connectors/pyredis/_utils.py
polycrud/constants.py
polycrud/entity/__init__.py
polycrud/entity/base.py
polycrud/exceptions.py
polycrud/py.typed
polycrud/utils/__init__.py
polycrud/utils/helper.py
polycrud/utils/print_utils.py
polycrud/utils/profiler.py
polycrud-1.0.1.dist-info/METADATA
polycrud-1.0.1.dist-info/WHEEL
polycrud-1.0.1.dist-info/RECORD
