Metadata-Version: 2.3
Name: polycrud
Version: 1.0.1
Summary: DB CRUD operations for Polybase
License: MIT
Author: haonv
Author-email: vanhao1915@gmail.com
Requires-Python: >=3.10,<4.0
Classifier: License :: OSI Approved :: MIT License
Classifier: Programming Language :: Python :: 3
Classifier: Programming Language :: Python :: 3.10
Classifier: Programming Language :: Python :: 3.11
Classifier: Programming Language :: Python :: 3.12
Classifier: Programming Language :: Python :: 3.13
Requires-Dist: aiohttp (>=3.11.16,<4.0.0)
Requires-Dist: cachine (>=0.1.0rc1,<0.2.0)
Requires-Dist: colorama (>=0.4.6,<0.5.0)
Requires-Dist: colored (>=2.2.4,<3.0.0)
Requires-Dist: orjson (>=3.10.16,<4.0.0)
Requires-Dist: pydantic (>=2.11.5,<3.0.0)
Requires-Dist: pydash (>=8.0.4,<9.0.0)
